opentelemetry/instrumentation/sklearn/__init__.py
opentelemetry/instrumentation/sklearn/package.py
opentelemetry/instrumentation/sklearn/version.py
opentelemetry_instrumentation_sklearn-0.45b0.dist-info/METADATA
opentelemetry_instrumentation_sklearn-0.45b0.dist-info/WHEEL
opentelemetry_instrumentation_sklearn-0.45b0.dist-info/entry_points.txt
opentelemetry_instrumentation_sklearn-0.45b0.dist-info/licenses/LICENSE
opentelemetry_instrumentation_sklearn-0.45b0.dist-info/RECORD
