Metadata-Version: 2.3
Name: opentelemetry-instrumentation-sklearn
Version: 0.45b0
Summary: OpenTelemetry sklearn instrumentation
Project-URL: Homepage, https://github.com/open-telemetry/opentelemetry-python-contrib/tree/main/instrumentation/opentelemetry-instrumentation-sklearn
Author-email: OpenTelemetry Authors <cncf-opentelemetry-contributors@lists.cncf.io>
License-Expression: Apache-2.0
License-File: LICENSE
Classifier: Development Status :: 4 - Beta
Classifier: Intended Audience :: Developers
Classifier: License :: OSI Approved :: Apache Software License
Classifier: Programming Language :: Python
Classifier: Programming Language :: Python :: 3
Classifier: Programming Language :: Python :: 3.8
Classifier: Programming Language :: Python :: 3.9
Classifier: Programming Language :: Python :: 3.10
Classifier: Programming Language :: Python :: 3.11
Requires-Python: >=3.8
Requires-Dist: opentelemetry-api~=1.12
Requires-Dist: opentelemetry-instrumentation==0.45b0
Provides-Extra: instruments
Requires-Dist: scikit-learn~=0.24.0; extra == 'instruments'
